bagsy/__init__.py
bagsy/__main__.py
bagsy/logger.py
bagsy/parser.py
bagsy/std.py
bagsy/convert/__init__.py
bagsy/convert/__main__.py
bagsy/convert/rosmsg.py
bagsy/info/__init__.py
bagsy/info/__main__.py
bagsy-0.5.1.dist-info/licenses/LICENSE
bagsy-0.5.1.dist-info/METADATA
bagsy-0.5.1.dist-info/WHEEL
bagsy-0.5.1.dist-info/entry_points.txt
bagsy-0.5.1.dist-info/top_level.txt
bagsy-0.5.1.dist-info/RECORD
