Metadata-Version: 2.4
Name: bagsy
Version: 0.5.1
Summary: A cli tool to help in the creation, conversion and sharing of rosbags
Author-email: Seb-sti1 <sebastien.kerbourch@ensta.fr>
License-Expression: Apache-2.0
Project-URL: Homepage, https://gitlab.ensta.fr/ssh/bagsy
Project-URL: Documentation, https://gitlab.ensta.fr/ssh/bagsy/-/blob/main/README.md
Project-URL: Repository, https://gitlab.ensta.fr/ssh/bagsy.git
Project-URL: Issues, https://gitlab.ensta.fr/ssh/bagsy/-/issues
Classifier: Development Status :: 2 - Pre-Alpha
Classifier: Environment :: Console
Classifier: Programming Language :: Python :: 3
Classifier: Operating System :: Unix
Requires-Python: >=3.10
License-File: LICENSE
Requires-Dist: rosbags
Requires-Dist: numpy
Requires-Dist: opencv-contrib-python
Dynamic: license-file
